machina/__init__.py
machina/logger.py
machina/loss_functional.py
machina/utils.py
machina/algos/__init__.py
machina/algos/airl.py
machina/algos/behavior_clone.py
machina/algos/ddpg.py
machina/algos/diayn.py
machina/algos/diayn_sac.py
machina/algos/gail.py
machina/algos/mpc.py
machina/algos/on_pol_teacher_distill.py
machina/algos/ppo_clip.py
machina/algos/ppo_kl.py
machina/algos/prioritized_ddpg.py
machina/algos/qtopt.py
machina/algos/r2d2_sac.py
machina/algos/sac.py
machina/algos/svg.py
machina/algos/trpo.py
machina/algos/vpg.py
machina/envs/__init__.py
machina/envs/ac_in_ob_env.py
machina/envs/continuous2discrete_env.py
machina/envs/env_utils.py
machina/envs/gym_env.py
machina/envs/rew_in_ob_env.py
machina/envs/skill_env.py
machina/models/__init__.py
machina/models/base.py
machina/models/deterministic_state_model.py
machina/noise/__init__.py
machina/noise/base.py
machina/noise/ounoise.py
machina/optims/__init__.py
machina/optims/adamw.py
machina/optims/distributed_adamw.py
machina/optims/distributed_sgd.py
machina/pds/__init__.py
machina/pds/base.py
machina/pds/categorical_pd.py
machina/pds/deterministic_pd.py
machina/pds/gaussian_pd.py
machina/pds/mixture_gaussian_pd.py
machina/pds/multi_categorical_pd.py
machina/pols/__init__.py
machina/pols/argmax_qf_pol.py
machina/pols/base.py
machina/pols/categorical_pol.py
machina/pols/deterministic_action_noise_pol.py
machina/pols/gaussian_pol.py
machina/pols/mixture_gaussian_pol.py
machina/pols/mpc_pol.py
machina/pols/multi_categorical_pol.py
machina/pols/random_pol.py
machina/prepro/__init__.py
machina/prepro/base.py
machina/samplers/__init__.py
machina/samplers/distributed_epi_sampler.py
machina/samplers/epi_sampler.py
machina/traj/__init__.py
machina/traj/epi_functional.py
machina/traj/traj.py
machina/traj/traj_functional.py
machina/vfuncs/__init__.py
machina/vfuncs/state_action_vfuncs/__init__.py
machina/vfuncs/state_action_vfuncs/base.py
machina_rl-0.2.1.dist-info/DESCRIPTION.rst
machina_rl-0.2.1.dist-info/METADATA
machina_rl-0.2.1.dist-info/RECORD
machina_rl-0.2.1.dist-info/WHEEL
machina_rl-0.2.1.dist-info/metadata.json
machina_rl-0.2.1.dist-info/top_level.txt
