Metadata-Version: 2.0
Name: machina-rl
Version: 0.2.1
Summary: machina is a library for a deep reinforcement learning.
Home-page: https://github.com/DeepX-inc/machina
Author: Reiji Hatsugai
Author-email: reiji.hatsugai@deepx.co.jp
License: MIT License
Platform: UNKNOWN
Requires-Dist: cached-property
Requires-Dist: torch (>=1.0.1)
Requires-Dist: joblib (>=0.11)
Requires-Dist: cloudpickle
Requires-Dist: redis
Requires-Dist: gym (==0.10.5)
Requires-Dist: numpy (>=1.13.3)
Requires-Dist: terminaltables
Requires-Dist: pandas
